MANIFEST.in
setup.py
leap/LICENSE.md
leap/README.md
leap/__init__.py
leap/calc_h2.py
leap/calc_h2.pyc
leap/eigenDecompose.py
leap/eigenDecompose.pyc
leap/findRelated.py
leap/findRelated.pyc
leap/leapMain.py
leap/leapMain.pyc
leap/leapUtils.py
leap/leapUtils.pyc
leap/leap_gwas.py
leap/leap_gwas.pyc
leap/probit.py
leap/probit.pyc
leap/regression/Leap_example.ipynb
leap/regression/README.md
leap/regression/__init__.py
leap/regression/calc_h2.py
leap/regression/calc_h2.pyc
leap/regression/eigenDecompose.py
leap/regression/eigenDecompose.pyc
leap/regression/findRelated.py
leap/regression/leapMain.py
leap/regression/leapMain.pyc
leap/regression/leapUtils.py
leap/regression/leapUtils.pyc
leap/regression/leap_gwas.py
leap/regression/leap_pipeline.py
leap/regression/leap_pipeline.sh
leap/regression/test.py
leap/regression/dataset1/.pversion
leap/regression/dataset1/dataset1.bed
leap/regression/dataset1/dataset1.bim
leap/regression/dataset1/dataset1.cov
leap/regression/dataset1/dataset1.fam
leap/regression/dataset1/dataset1.phe
leap/regression/dataset1/dataset1.phe.liab
leap/regression/dataset1/output.liab_nofixed
leap/regression/dataset1/output.liab_nofixed2
leap/regression/dataset1/output.liabs
leap/regression/dataset1/extracts/chr10_extract.txt
leap/regression/dataset1/extracts/chr1_extract.txt
leap/regression/dataset1/extracts/chr2_extract.txt
leap/regression/dataset1/extracts/chr3_extract.txt
leap/regression/dataset1/extracts/chr4_extract.txt
leap/regression/dataset1/extracts/chr5_extract.txt
leap/regression/dataset1/extracts/chr6_extract.txt
leap/regression/dataset1/extracts/chr7_extract.txt
leap/regression/dataset1/extracts/chr8_extract.txt
leap/regression/dataset1/extracts/chr9_extract.txt
leap/regression/dataset1/extracts/nochr10_extract.txt
leap/regression/dataset1/extracts/nochr1_extract.txt
leap/regression/dataset1/extracts/nochr2_extract.txt
leap/regression/dataset1/extracts/nochr3_extract.txt
leap/regression/dataset1/extracts/nochr4_extract.txt
leap_gwas.egg-info/PKG-INFO
leap_gwas.egg-info/SOURCES.txt
leap_gwas.egg-info/dependency_links.txt
leap_gwas.egg-info/requires.txt
leap_gwas.egg-info/top_level.txt