Metadata-Version: 1.0
Name: leap-gwas
Version: 0.1.8.1
Summary: Liability Estimation in Case Control Studies
Home-page: https://github.com/omerwe/LEAP
Author: Omer Weissbrod
Author-email: omerw@cs.technion.ac.il
License: Apache 2.0
Keywords: gwas bioinformatics LMMs MLMs
Platform: UNKNOWN
